{"color": "#cc79f3", "children": [{"color": "#79f380", "children": [{"color": "#a379f3", "children": [{"color": "#f3ef79", "children": [{"color": "#a379f3", "children": [{"color": "#a379f3", "name": "Leif Halvard Silli", "id": "48B313A8.7090009@malform.no"}], "name": "Leif Halvard Silli", "id": "48B31156.2010403@Rhul.Ac.Uk"}], "name": "Philip TAYLOR", "id": "48B30EF6.3020502@malform.no"}, {"color": "#f3ef79", "children": [{"color": "#f3ef79", "name": "Philip TAYLOR", "id": "48B30EAB.80405@Rhul.Ac.Uk"}], "name": "Philip TAYLOR", "id": "p06240800c4d8bb9040e9@[17.202.35.52]"}], "name": "Leif Halvard Silli", "id": "48B302DB.7020206@Rhul.Ac.Uk"}], "name": "Philip TAYLOR (Ret'd", "id": "p06240809c4d8aae385e6@[192.168.1.111]"}, {"color": "#79f3c1", "name": "Ben Boyle", "id": "5f37426b0808250822t147954f3x87e4480aab31d1fc@mail.gmail.com"}, {"color": "#f3c779", "children": [{"color": "#a379f3", "children": [{"color": "#79e2f3", "children": [{"color": "#f3ef79", "children": [{"color": "#79e2f3", "children": [{"color": "#f3ef79", "children": [{"color": "#f3ef79", "name": "Philip TAYLOR", "id": "48B2D8FF.2000005@Rhul.Ac.Uk"}], "name": "Philip TAYLOR", "id": "op.ugf9cgdi64w2qv@annevk-t60.oslo.opera.com"}], "name": "Anne van Kesteren", "id": "48B2D516.7080202@Rhul.Ac.Uk"}], "name": "Philip TAYLOR", "id": "op.ugf8scx564w2qv@annevk-t60.oslo.opera.com"}], "name": "Anne van Kesteren", "id": "48B2D27B.1030007@Rhul.Ac.Uk"}, {"color": "#f3ad79", "children": [{"color": "#f3ad79", "name": "Robert J Burns", "id": "F37B1267-C9E4-4C84-9B73-148AA3FE5690@robburns.com"}, {"color": "#8cf379", "children": [{"color": "#7a79f3", "children": [{"color": "#ddf379", "name": "Maurice", "id": "690C1EB2-88AC-4EE3-A561-316E6424646E@thymeonline.com"}, {"color": "#cc79f3", "children": [{"color": "#7a79f3", "children": [{"color": "#8cf379", "children": [{"color": "#7a79f3", "children": [{"color": "#7a79f3", "children": [{"color": "#79e2f3", "children": [{"color": "#a379f3", "children": [{"color": "#7a79f3", "name": "Boris Zbarsky", "id": "48B31C4F.90903@mit.edu"}, {"color": "#a379f3", "name": "Leif Halvard Silli", "id": "48B3371A.9010006@malform.no"}, {"color": "#79e2f3", "children": [{"color": "#f3c779", "children": [{"color": "#f3ef79", "name": "Philip TAYLOR", "id": "48BC1D3A.8030506@Rhul.Ac.Uk"}, {"color": "#a379f3", "children": [{"color": "#f3c779", "children": [{"color": "#f3ad79", "children": [{"color": "#f379af", "children": [{"color": "#a379f3", "children": [{"color": "#a379f3", "children": [{"color": "#79f3ea", "children": [{"color": "#a379f3", "children": [{"color": "#f379af", "name": "Lachlan Hunt", "id": "48BDD646.2080302@lachy.id.au"}, {"color": "#cc79f3", "children": [{"color": "#f3ad79", "children": [{"color": "#cc79f3", "children": [{"color": "#f379af", "children": [{"color": "#e579f3", "children": [{"color": "#f379af", "children": [{"color": "#e579f3", "children": [{"color": "#a379f3", "children": [{"color": "#e579f3", "children": [{"color": "#a379f3", "children": [{"color": "#f379bf", "children": [{"color": "#a379f3", "children": [{"color": "#a379f3", "name": "Leif Halvard Silli", "id": "48C1D345.5020904@malform.no"}], "name": "Leif Halvard Silli", "id": "1A986F50-49FD-414A-BDD9-4A062190FACA@apple.com"}, {"color": "#f379af", "children": [{"color": "#f379af", "name": "Lachlan Hunt", "id": "48C13DE8.8070207@lachy.id.au"}], "name": "Lachlan Hunt", "id": "A21A773C3F9742F18CA87F768DDC4B0D@HANDS"}], "name": "James Craig", "id": "48C131EC.1060600@malform.no"}], "name": "Leif Halvard Silli", "id": "384F8498AF324B6E9391B0A9B3E1C5A4@HANDS"}], "name": "David Poehlman", "id": "48C06D60.7080508@malform.no"}, {"color": "#f37996", "children": [{"color": "#f379af", "children": [{"color": "#a379f3", "children": [{"color": "#f379bf", "children": [{"color": "#f37996", "children": [{"color": "#f379bf", "children": [{"color": "#a379f3", "children": [{"color": "#f379bf", "children": [{"color": "#a379f3", "children": [{"color": "#f379bf", "children": [{"color": "#a379f3", "children": [{"color": "#a379f3", "name": "Leif Halvard Silli", "id": "48C49D8B.9090202@malform.no"}], "name": "Leif Halvard Silli", "id": "11B2537A-7DD5-4FD8-A4B3-E6D9CAE2A11E@apple.com"}], "name": "James Craig", "id": "48C40029.6040509@malform.no"}], "name": "Leif Halvard Silli", "id": "9659D77C-DE25-4F6D-A42B-3B17FB9AC43F@apple.com"}], "name": "James Craig", "id": "48C20154.2070205@malform.no"}], "name": "Leif Halvard Silli", "id": "B9B7EE3D-9E25-4D73-9F4E-6E1857A39C3F@apple.com"}], "name": "James Craig", "id": "120201c90f9c$70a535c0$51efa140$@com"}, {"color": "#8cf379", "children": [{"color": "#f37996", "children": [{"color": "#8cf379", "children": [{"color": "#e579f3", "children": [{"color": "#f3c779", "children": [{"color": "#f3c779", "name": "Justin James", "id": "13b301c911c1$59fe7b20$0dfb7160$@com"}], "name": "Justin James", "id": "DD265376E0DF4157A43E84620CF4A532@HANDS"}], "name": "David Poehlman", "id": "6F0325EE-C0E9-45E7-92A6-DA4F55E38DC9@iki.fi"}, {"color": "#f3ad79", "children": [{"color": "#a379f3", "name": "Leif Halvard Silli", "id": "48C486B2.7040701@malform.no"}, {"color": "#f3ad79", "name": "Robert J Burns", "id": "350D86D8-08B7-457C-8F89-759CFB3192D1@robburns.com"}, {"color": "#f379bf", "children": [{"color": "#f37996", "children": [{"color": "#79f3c1", "children": [{"color": "#f37996", "children": [{"color": "#f37996", "name": "John Foliot", "id": "007a01c911e9$f8085e80$1b2e42ab@stanford.edu"}], "name": "John Foliot", "id": "FB3F6A55-4C7B-4E36-93A8-3B786C16EA9F@apple.com"}, {"color": "#f37996", "name": "John Foliot", "id": "006d01c911e2$cd02be80$1b2e42ab@stanford.edu"}, {"color": "#79f3c1", "name": "Ben Boyle", "id": "5f37426b0809090627p78ec8865j56dce9bfb0941a0b@mail.gmail.com"}], "name": "Ben Boyle", "id": "006801c911e1$7924abd0$1b2e42ab@stanford.edu"}, {"color": "#e579f3", "children": [{"color": "#e579f3", "name": "David Poehlman", "id": "A944664E496643F792671263676A8709@HANDS"}], "name": "David Poehlman", "id": "48C4E4B7.6020107@lachy.id.au"}, {"color": "#f3ad79", "name": "Robert J Burns", "id": "6A88FBE5-B25B-4F98-889C-C8359BBADBFF@robburns.com"}], "name": "John Foliot", "id": "17E7F546-45E3-4AA2-BA17-5B4F6ADEC0A2@apple.com"}], "name": "James Craig", "id": "00fd01c9114e$19f92750$863c42ab@stanford.edu"}], "name": "Robert J Burns", "id": "48C450A2.50407@lachy.id.au"}], "name": "Henri Sivonen", "id": "00e501c91113$54b7c3f0$863c42ab@stanford.edu"}, {"color": "#8cf379", "children": [{"color": "#8cf379", "name": "Henri Sivonen", "id": "3B426AD0-785B-4A58-8469-13BC6D198BF4@iki.fi"}, {"color": "#a379f3", "children": [{"color": "#8cf379", "children": [{"color": "#a379f3", "children": [{"color": "#a379f3", "name": "Leif Halvard Silli", "id": "48C46F59.3010909@malform.no"}], "name": "Leif Halvard Silli", "id": "48C4313B.90605@lachy.id.au"}, {"color": "#79f3a8", "children": [{"color": "#f3ad79", "name": "Robert J Burns", "id": "61E67E9D-8037-41D1-BEC6-975AB13842C7@robburns.com"}, {"color": "#8cf379", "children": [{"color": "#79f3a8", "children": [{"color": "#e579f3", "children": [{"color": "#a379f3", "name": "Leif Halvard Silli", "id": "48C695B1.3020608@malform.no"}, {"color": "#a379f3", "children": [{"color": "#f3ad79", "children": [{"color": "#79f380", "children": [{"color": "#a379f3", "children": [{"color": "#79f380", "children": [{"color": "#79f380", "name": "Philip TAYLOR (Ret'd", "id": "48C6CE02.9010302@Rhul.Ac.Uk"}], "name": "Philip TAYLOR (Ret'd", "id": "151101c912ac$ca4675e0$5ed361a0$@com"}, {"color": "#e579f3", "children": [{"color": "#e579f3", "name": "David Poehlman", "id": "B77BD82E5D7E44998BC9B963FB3EDA26@HANDS"}], "name": "David Poehlman", "id": "48C72ECE.7070001@malform.no"}], "name": "Leif Halvard Silli", "id": "48C6BB72.2090900@Rhul.Ac.Uk"}], "name": "Philip TAYLOR (Ret'd", "id": "FC471526FD3E4814B956823E75E2D120@HANDS"}, {"color": "#f3ad79", "name": "Robert J Burns", "id": "A373267A-44A0-4008-9C33-D258E93C6B7D@robburns.com"}], "name": "Robert J Burns", "id": "48C6B301.1080409@malform.no"}], "name": "Leif Halvard Silli", "id": "FDB580D6EEFC4C908D0155BD0E9339E1@HANDS"}], "name": "David Poehlman", "id": "48C69426.7040107@malform.no"}, {"color": "#e579f3", "name": "David Poehlman", "id": "0B9CDE4D9A6B4C5981F194B5032205D1@HANDS"}, {"color": "#8cf379", "children": [{"color": "#f37996", "children": [{"color": "#f37996", "name": "John Foliot", "id": "000501c91380$83e3b610$0a00000a@stanford.edu"}], "name": "John Foliot", "id": "CDC95180-CD3A-436A-B758-4466494EA10B@iki.fi"}], "name": "Henri Sivonen", "id": "C4EC27AA.E207%mattmay@adobe.com"}], "name": "Matt Morgan-May", "id": "A4CA8F64-6DDE-451A-B2E6-D14CD4B56B3D@iki.fi"}], "name": "Henri Sivonen", "id": "C4EAE6B3.E0D9%mattmay@adobe.com"}, {"color": "#e579f3", "name": "David Poehlman", "id": "2F8651AFBB0A4AD3B36644AF4932D0D8@HANDS"}], "name": "Matt Morgan-May", "id": "1266DF95-C5C3-46B3-A583-7544EAA3CD0F@iki.fi"}], "name": "Henri Sivonen", "id": "48C42C04.8070202@malform.no"}], "name": "Leif Halvard Silli", "id": "7ED0CF25-D7E1-4D2B-9B30-E89920B10FA4@iki.fi"}], "name": "Henri Sivonen", "id": "85107C86198A423CBC34B6A3D850DD70@HANDS"}], "name": "John Foliot", "id": "934BAE1E-E518-4DC3-B48F-0A2B94097842@iki.fi"}], "name": "Henri Sivonen", "id": "00b601c91072$1e5bf930$863c42ab@stanford.edu"}], "name": "John Foliot", "id": "C58671D2-C9C9-4FEF-980F-BCC312575E0B@apple.com"}, {"color": "#f37996", "children": [{"color": "#f379af", "children": [{"color": "#e579f3", "children": [{"color": "#f379af", "children": [{"color": "#e579f3", "children": [{"color": "#e579f3", "name": "David Poehlman", "id": "1F59936B66BB419F879155DD3CBE1F11@HANDS"}, {"color": "#f379af", "children": [{"color": "#e579f3", "children": [{"color": "#f379af", "children": [{"color": "#e579f3", "children": [{"color": "#e579f3", "name": "David Poehlman", "id": "C0E0C4E250384C238A545F405364D4F5@HANDS"}, {"color": "#b4f379", "children": [{"color": "#b4f379", "name": "Steven Faulkner", "id": "55687cf80809060433g65fba923o59917ae2e4c66a1b@mail.gmail.com"}], "name": "Steven Faulkner", "id": "55687cf80809060431p65403b3fs8f644902d2b0d770@mail.gmail.com"}], "name": "David Poehlman", "id": "48C262EB.20709@lachy.id.au"}], "name": "Lachlan Hunt", "id": "55687cf80809060334u779b9fc7xf2be15548d77fcfd@mail.gmail.com"}, {"color": "#f379af", "children": [{"color": "#b4f379", "children": [{"color": "#f379d8", "children": [{"color": "#f3c779", "children": [{"color": "#f3c779", "name": "Justin James", "id": "128c01c9102b$27fbc7a0$77f356e0$@com"}], "name": "Justin James", "id": "48C2750A.2010300@cfit.ie"}], "name": "Joshue O Connor", "id": "55687cf80809060510y98fbee7g9d91bc8b191ac279@mail.gmail.com"}], "name": "Steven Faulkner", "id": "48C26D64.1010201@cfit.ie"}, {"color": "#f39e79", "children": [{"color": "#f3c779", "children": [{"color": "#f39e79", "children": [{"color": "#f39e79", "name": "Laura Carlson", "id": "1c8dbcaa0809061240u6a091301wba7149912ab01398@mail.gmail.com"}, {"color": "#b4f379", "name": "Steven Faulkner", "id": "55687cf80809061215q13b449n49c0d99b6cfdf1fd@mail.gmail.com"}], "name": "Laura Carlson", "id": "96D02BA7-ADE6-43B4-B198-AB8D0FB170B7@googlemail.com"}, {"color": "#f3c779", "name": "Justin James", "id": "12be01c9108c$b91b9bf0$2b52d3d0$@com"}], "name": "Justin James", "id": "1c8dbcaa0809060522n5ca2f98dpc78c8b30dc58d553@mail.gmail.com"}], "name": "Laura Carlson", "id": "48C26EB6.7010303@lachy.id.au"}], "name": "Lachlan Hunt", "id": "1c8dbcaa0809060436r772a197ge2906b6b1bbfe6ef@mail.gmail.com"}, {"color": "#e579f3", "name": "David Poehlman", "id": "0391DC98AF9B49A89A684F034BEFE0FA@HANDS"}], "name": "David Poehlman", "id": "48C2573E.4070406@lachy.id.au"}], "name": "Lachlan Hunt", "id": "55687cf80809060213j5ca9d5av5198229c8b77b160@mail.gmail.com"}], "name": "David Poehlman", "id": "48C247FC.2070901@lachy.id.au"}], "name": "Lachlan Hunt", "id": "78328FEF3B3640FDBCB38D6FFE8D3072@HANDS"}], "name": "David Poehlman", "id": "48C1A4B9.3080303@lachy.id.au"}], "name": "Lachlan Hunt", "id": "004401c90f79$ba4c93d0$863c42ab@stanford.edu"}], "name": "John Foliot", "id": "48C10A96.4050709@lachy.id.au"}], "name": "James Craig", "id": "004901c90f12$211286a0$4c2f42ab@stanford.edu"}, {"color": "#f379af", "children": [{"color": "#a379f3", "children": [{"color": "#a379f3", "name": "Leif Halvard Silli", "id": "48C1C05F.8010202@malform.no"}], "name": "Leif Halvard Silli", "id": "48C15F83.3080907@lachy.id.au"}], "name": "Lachlan Hunt", "id": "48C1507B.6090209@malform.no"}], "name": "Leif Halvard Silli", "id": "48C06FA8.6000400@lachy.id.au"}], "name": "Lachlan Hunt", "id": "936AB3BBA24445A0935E49DA2BE3336A@HANDS"}, {"color": "#f379af", "children": [{"color": "#f37996", "children": [{"color": "#f3ef79", "name": "Philip TAYLOR", "id": "48C2CE3A.7020809@Rhul.Ac.Uk"}, {"color": "#f37996", "name": "John Foliot", "id": "00af01c91065$027a7190$863c42ab@stanford.edu"}, {"color": "#e579f3", "name": "David Poehlman", "id": "0D1345991FA04A24A8ED6C045621056C@HANDS"}], "name": "John Foliot", "id": "48C2CD48.2020106@lachy.id.au"}], "name": "Lachlan Hunt", "id": "00a501c9103a$f30071d0$863c42ab@stanford.edu"}], "name": "John Foliot", "id": "48C065E9.7040905@lachy.id.au"}], "name": "Leif Halvard Silli", "id": "38D099D6E8274D459B439A62C5189CB6@HANDS"}], "name": "David Poehlman", "id": "48C05E12.6020102@lachy.id.au"}], "name": "Lachlan Hunt", "id": "9DD92BE4250B4464B62FD9C44ECC28F5@HANDS"}], "name": "David Poehlman", "id": "48C05A5C.1040705@lachy.id.au"}], "name": "Lachlan Hunt", "id": "48C03222.9030907@googlemail.com"}, {"color": "#f379af", "children": [{"color": "#f379af", "name": "Lachlan Hunt", "id": "48C7E5BA.1020603@lachy.id.au"}], "name": "Lachlan Hunt", "id": "p06240815c4ecaa313430@[10.0.1.8]"}], "name": "Dave Singer", "id": "48BFC4FD.7020406@lachy.id.au"}, {"color": "#7991f3", "children": [{"color": "#8cf379", "children": [{"color": "#f3ef79", "name": "Philip TAYLOR", "id": "48C96123.6060904@Rhul.Ac.Uk"}, {"color": "#f379af", "children": [{"color": "#f379af", "name": "Lachlan Hunt", "id": "48CA3737.8080503@lachy.id.au"}], "name": "Lachlan Hunt", "id": "C1E2AB01-7A7A-4D44-BA09-979BE4987F88@iki.fi"}], "name": "Henri Sivonen", "id": "18633.24184.890417.208963@retriever.corp.google.com"}, {"color": "#8a79f3", "children": [{"color": "#8a79f3", "name": "Schnabel, Stefan", "id": "E34714E1E6587741AD32C8E445B6F4AB512CEE@dewdfe1o.wdf.sap.corp"}, {"color": "#8cf379", "children": [{"color": "#f3c779", "children": [{"color": "#79baf3", "children": [{"color": "#f38579", "children": [{"color": "#f38579", "name": "Dailey, David P.", "id": "1835D662B263BC4E864A7CFAB2FEEB3D017D27C0@msfexch01.srunet.sruad.edu"}], "name": "Dailey, David P.", "id": "1e3451610809120839h19febf1cgd9ede4073235726e@mail.gmail.com"}], "name": "William Loughborough", "id": "024301c914e6$c3f13bd0$4bd3b370$@com"}], "name": "Justin James", "id": "E8516281-4BA5-46C4-9824-940B4F76BD52@iki.fi"}], "name": "Henri Sivonen", "id": "01ec01c91486$78cec600$6a6c5200$@com"}], "name": "Schnabel, Stefan", "id": "op.uhccfxa8wxe0ny@widsith"}, {"color": "#7991f3", "name": "Al Gilman", "id": "575AE52E-9403-472D-850E-3B15DF8C4AC3@IEEE.org"}, {"color": "#f38579", "children": [{"color": "#f38579", "name": "Dailey, David P.", "id": "1835D662B263BC4E864A7CFAB2FEEB3D015255D2@msfexch01.srunet.sruad.edu"}], "name": "Dailey, David P.", "id": "p06240808c4ef4e741fa3@[17.202.35.52]"}], "name": "Al Gilman", "id": "7805B32F-7E4E-452A-B980-70233BFFEEF2@iki.fi"}, {"color": "#f3c779", "name": "Justin James", "id": "100f01c90e44$24248d30$6c6da790$@com"}, {"color": "#cc79f3", "children": [{"color": "#a379f3", "children": [{"color": "#cc79f3", "children": [{"color": "#8cf379", "children": [{"color": "#8cf379", "name": "Henri Sivonen", "id": "956B6491-97E4-4D6C-9340-70A73B4B53AA@iki.fi"}], "name": "Henri Sivonen", "id": "p06240819c4ecb3224cb3@[10.0.1.8]"}], "name": "Dave Singer", "id": "48C7025A.5070907@malform.no"}], "name": "Leif Halvard Silli", "id": "p06240813c4eca7eeac7b@[10.0.1.8]"}, {"color": "#8cf379", "children": [{"color": "#9bf379", "children": [{"color": "#8cf379", "children": [{"color": "#8cf379", "name": "Henri Sivonen", "id": "AB1E016A-51BE-4E6A-9335-E68C944BDF18@iki.fi"}], "name": "Henri Sivonen", "id": "7BE8BB95-23DA-4089-8B21-7E9232837F19@apple.com"}], "name": "Eric Carlson", "id": "5BDFC1DD-18C5-4714-B373-32702406C650@iki.fi"}], "name": "Henri Sivonen", "id": "5C9276BE-B77A-453F-AE07-723FA2B2AEFF@apple.com"}, {"color": "#79d3f3", "children": [{"color": "#79d3f3", "name": "Cindy Sue Causey", "id": "dbdb69c90809041334g163903b7m427e51ba7bc93efd@mail.gmail.com"}, {"color": "#e579f3", "name": "David Poehlman", "id": "D7C6163FB3274607AB3887536CBD016C@HANDS"}, {"color": "#cc79f3", "children": [{"color": "#f37996", "name": "John Foliot", "id": "000101c90ed4$d2659ca0$4c2f42ab@stanford.edu"}, {"color": "#cc79f3", "name": "Dave Singer", "id": "p06240814c4eca9900e54@[10.0.1.8]"}], "name": "Dave Singer", "id": "8F8BB8B3-C532-48F7-A2FA-FB974440B566@iki.fi"}], "name": "Cindy Sue Causey", "id": "5f37426b0809040315w3b5ef308sa9aa823341a684b4@mail.gmail.com"}], "name": "Dave Singer", "id": "EDCEF565-8938-4955-AC76-30B1B88D7ECD@iki.fi"}, {"color": "#f3ad79", "name": "Robert J Burns", "id": "BCB72E32-1FB0-4774-A5BF-2AD1E63B1E76@robburns.com"}], "name": "Robert J Burns", "id": "p06240872c4e4b9d5c033@[10.0.1.8]"}], "name": "Dave Singer", "id": "48BDDE72.7040107@malform.no"}], "name": "Leif Halvard Silli", "id": "20080902231119.GA32419@stripey.com"}], "name": "Smylers", "id": "48BD84E7.7000904@malform.no"}], "name": "Leif Halvard Silli", "id": "20080902145832.GN2588@stripey.com"}, {"color": "#8cf379", "children": [{"color": "#8cf379", "name": "Henri Sivonen", "id": "B6C2B091-35AA-4013-AA9E-F8894E63D8B8@iki.fi"}, {"color": "#f3c779", "children": [{"color": "#f3c779", "name": "Justin James", "id": "0e8601c90cfb$644c81f0$2ce585d0$@com"}], "name": "Justin James", "id": "48BD2C9B.2030208@lachy.id.au"}], "name": "Henri Sivonen", "id": "48BD27DF.9090005@earthlink.net"}, {"color": "#a379f3", "name": "Leif Halvard Silli", "id": "48BD7A55.3060104@malform.no"}], "name": "Leif Halvard Silli", "id": "48BD213B.2030807@lachy.id.au"}], "name": "Lachlan Hunt", "id": "48BC7FF1.9040402@malform.no"}, {"color": "#f3ad79", "name": "Robert J Burns", "id": "95A49D74-F01A-484B-B0C0-D22963904108@robburns.com"}], "name": "Robert J Burns", "id": "48BC604F.1010809@lachy.id.au"}, {"color": "#f3c779", "name": "Justin James", "id": "0e3001c90cb7$2e3da470$8ab8ed50$@com"}], "name": "Justin James", "id": "48BC4F28.9010402@malform.no"}], "name": "Leif Halvard Silli", "id": "0dd301c90c5a$099d3f20$1cd7bd60$@com"}], "name": "Justin James", "id": "48BC0FAF.7080707@lachy.id.au"}, {"color": "#f3ef79", "children": [{"color": "#f3ef79", "name": "Philip TAYLOR", "id": "48B31BAD.9000709@Rhul.Ac.Uk"}], "name": "Philip TAYLOR", "id": "op.uggmslxb64w2qv@annevk-t60.oslo.opera.com"}], "name": "Anne van Kesteren", "id": "48B319F8.5090201@Rhul.Ac.Uk"}], "name": "Leif Halvard Silli", "id": "op.uggma0pa64w2qv@annevk-t60.oslo.opera.com"}], "name": "Anne van Kesteren", "id": "48B3167A.8090008@mit.edu"}], "name": "Boris Zbarsky", "id": "op.ugglgqva64w2qv@annevk-t60.oslo.opera.com"}, {"color": "#7a79f3", "name": "Boris Zbarsky", "id": "48B31650.4090608@mit.edu"}], "name": "Boris Zbarsky", "id": "D1FB3F27-D2DF-44A9-BED2-356011BBB9EA@iki.fi"}, {"color": "#7a79f3", "children": [{"color": "#cc79f3", "children": [{"color": "#7a79f3", "children": [{"color": "#cc79f3", "children": [{"color": "#7a79f3", "children": [{"color": "#7a79f3", "name": "Boris Zbarsky", "id": "48B4BB2A.5010607@mit.edu"}], "name": "Boris Zbarsky", "id": "p06240825c4da3d46a6ef@[17.202.35.52]"}], "name": "Dave Singer", "id": "48B3FDC5.4070007@mit.edu"}], "name": "Boris Zbarsky", "id": "p06240801c4d8d16a6017@[17.202.35.52]"}], "name": "Dave Singer", "id": "48B31636.2060507@mit.edu"}], "name": "Boris Zbarsky", "id": "48B301AE.3000404@cam.ac.uk"}, {"color": "#cc79f3", "name": "Dave Singer", "id": "p0624080cc4d8af428c34@[192.168.1.111]"}], "name": "Henri Sivonen", "id": "48B2FDA6.3020504@mit.edu"}], "name": "Boris Zbarsky", "id": "p0624080ac4d8ac65e066@[192.168.1.111]"}], "name": "Dave Singer", "id": "48B2FB25.30209@mit.edu"}], "name": "Boris Zbarsky", "id": "B3F1F10C-0D34-4282-9112-877738D3DFE0@iki.fi"}], "name": "Henri Sivonen", "id": "48B2F08A.1050300@mit.edu"}], "name": "Robert J Burns", "id": "48B2E097.3080907@malform.no"}], "name": "Leif Halvard Silli", "id": "op.ugf77kwb64w2qv@annevk-t60.oslo.opera.com"}, {"color": "#f3c779", "name": "Justin James", "id": "093201c906f0$0f1ff4c0$2d5fde40$@com"}], "name": "Justin James", "id": "3b31caf90808250819w6f911143wc6994a90a6c94b0b@mail.gmail.com"}], "name": "Dave Singer", "id": "08f401c906c2$b461cc20$1d256460$@com"}