{"assets":{"F09951806C44068639127C4319D17DDB":{"type":"texture","index":117,"assetRequest":{"type":"slide","state":"incoming","slide":"3FA2BF12-C78F-4E43-93EA-FE8D05FFCE5C"},"url":{"web":"assets/F09951806C44068639127C4319D17DDB.svg"},"width":1024,"height":768},"2925F72CEF6CB0C7E494FFFDAF60CF5B":{"type":"texture","index":116,"assetRequest":{"type":"slide","state":"outgoing","slide":"4EFA6628-35F4-47F2-8420-0EA67D914D47"},"url":{"web":"assets/2925F72CEF6CB0C7E494FFFDAF60CF5B.svg"},"width":1024,"height":768}},"events":[{"effects":[{"beginTime":0,"baseLayer":{"animations":[],"initialState":{"affineTransform":[1,0,0,1,0,0],"masksToBounds":false,"rotation":0,"scale":1,"position":{"pointX":512,"pointY":384},"width":1024,"sublayerTransform":[1,0,0,0,0,1,0,0,0,0,1,0,0,0,0,1],"contentsRect":{"y":0,"x":0,"width":1,"height":1},"opacity":1,"edgeAntialiasingMask":251658240,"height":768,"hidden":false,"anchorPoint":{"pointX":0.5,"pointY":0.5}},"objectID":"0","layers":[{"animations":[],"initialState":{"affineTransform":[1,0,0,1,0,0],"masksToBounds":false,"rotation":0,"scale":1,"position":{"pointX":512,"pointY":384},"width":1024,"sublayerTransform":[1,0,0,0,0,1,0,0,0,0,1,-0.0004922987690640373,0,0,0,1],"contentsRect":{"y":0,"x":0,"width":1,"height":1},"opacity":1,"edgeAntialiasingMask":251658240,"height":768,"hidden":false,"anchorPoint":{"pointX":0.5,"pointY":0.5}},"layers":[{"animations":[],"layers":[],"initialState":{"affineTransform":[1,0,0,1,0,0],"masksToBounds":false,"rotation":0,"scale":1,"position":{"pointX":512,"pointY":384},"width":1024,"sublayerTransform":[1,0,0,0,0,1,0,0,0,0,1,0,0,0,0,1],"contentsRect":{"y":0,"x":0,"width":1,"height":1},"opacity":1,"edgeAntialiasingMask":0,"height":768,"hidden":false,"anchorPoint":{"pointX":0.5,"pointY":0.5}},"texture":"F09951806C44068639127C4319D17DDB"},{"animations":[{"timeOffset":0,"from":{"scalar":false},"beginTime":0,"repeatCount":0,"fillMode":"both","property":"hidden","autoreverses":false,"duration":0.01,"to":{"scalar":true}}],"layers":[],"initialState":{"affineTransform":[1,0,0,1,0,0],"masksToBounds":false,"rotation":0,"scale":1,"position":{"pointX":512,"pointY":384},"width":1024,"sublayerTransform":[1,0,0,0,0,1,0,0,0,0,1,0,0,0,0,1],"contentsRect":{"y":0,"x":0,"width":1,"height":1},"opacity":1,"edgeAntialiasingMask":0,"height":768,"hidden":false,"anchorPoint":{"pointX":0.5,"pointY":0.5}},"texture":"2925F72CEF6CB0C7E494FFFDAF60CF5B"}]}]},"effects":[],"duration":0.01,"type":"transition","name":"none","objectID":"0"}],"automaticPlay":false,"hyperlinks":[],"accessibility":[{"text":"ordinal","targetRectangle":{"y":298.0310363769531,"x":849.0841217041016,"width":80.00390625,"height":29}},{"text":"discrete","targetRectangle":{"y":298.0740356445312,"x":342.3801727294922,"width":92.05078125,"height":29}},{"text":"types of variables","targetRectangle":{"y":18.21034669876099,"x":708.8298025131226,"width":284.076,"height":43}},{"text":"categorical","targetRectangle":{"y":153.3042602539062,"x":641.8240509033203,"width":126.7265625,"height":29}},{"text":"numerical ","targetRectangle":{"y":162.2808532714844,"x":210.1689758300781,"width":120.046875,"height":29}},{"text":"nominal","targetRectangle":{"y":298.2966918945312,"x":574.1891632080078,"width":92.00390625,"height":29}},{"text":"continuous","targetRectangle":{"y":298.3396911621094,"x":54.85236167907715,"width":129.31640625,"height":29}},{"text":"ud_comply: Percentage of user data requests Google complied with ","targetRectangle":{"y":695.934005022049,"x":86.70254516601557,"width":640.6352265625001,"height":62.00039672851562}},{"text":"all variables","targetRectangle":{"y":38.30806350708008,"x":418.5756378173828,"width":137.42578125,"height":29}}],"baseLayer":{"animations":[],"initialState":{"affineTransform":[1,0,0,1,0,0],"masksToBounds":false,"rotation":0,"scale":1,"position":{"pointX":512,"pointY":384},"width":1024,"sublayerTransform":[1,0,0,0,0,1,0,0,0,0,1,0,0,0,0,1],"contentsRect":{"y":0,"x":0,"width":1,"height":1},"opacity":1,"edgeAntialiasingMask":251658240,"height":768,"hidden":false,"anchorPoint":{"pointX":0.5,"pointY":0.5}},"objectID":"0","layers":[{"animations":[],"initialState":{"affineTransform":[1,0,0,1,0,0],"masksToBounds":false,"rotation":0,"scale":1,"position":{"pointX":512,"pointY":384},"width":1024,"sublayerTransform":[1,0,0,0,0,1,0,0,0,0,1,-0.0004922987690640373,0,0,0,1],"contentsRect":{"y":0,"x":0,"width":1,"height":1},"opacity":1,"edgeAntialiasingMask":251658240,"height":768,"hidden":false,"anchorPoint":{"pointX":0.5,"pointY":0.5}},"layers":[{"animations":[],"layers":[],"initialState":{"affineTransform":[1,0,0,1,0,0],"masksToBounds":false,"rotation":0,"scale":1,"position":{"pointX":512,"pointY":384},"width":1024,"sublayerTransform":[1,0,0,0,0,1,0,0,0,0,1,0,0,0,0,1],"contentsRect":{"y":0,"x":0,"width":1,"height":1},"opacity":1,"edgeAntialiasingMask":0,"height":768,"hidden":false,"anchorPoint":{"pointX":0.5,"pointY":0.5}},"texture":"2925F72CEF6CB0C7E494FFFDAF60CF5B"}]}]}}]}